dsbox/__init__.py
dsbox/dbconnection/__init__.py
dsbox/dbconnection/dbconnector.py
dsbox/dbconnection/plasma_connector.py
dsbox/examples/__init__.py
dsbox/examples/sales_prediction_usecase/__init__.py
dsbox/examples/sales_prediction_usecase/sales_prediction_dag.py
dsbox/examples/sales_prediction_usecase/ml/__init__.py
dsbox/examples/sales_prediction_usecase/ml/feature_engineering.py
dsbox/examples/sales_prediction_usecase/ml/modeling.py
dsbox/examples/tree_disease_usecase/__init__.py
dsbox/examples/tree_disease_usecase/tree_disease_dag.py
dsbox/examples/tree_disease_usecase/tree_disease_dag_with_pg.py
dsbox/examples/tree_disease_usecase/ml/__init__.py
dsbox/examples/tree_disease_usecase/ml/feature_engineering.py
dsbox/examples/tree_disease_usecase/ml/modeling.py
dsbox/examples/tree_disease_usecase/ml/sub_dags.py
dsbox/kube/__init__.py
dsbox/kube/data_operations.py
dsbox/kube/process_data.py
dsbox/ml/__init__.py
dsbox/ml/metrics.py
dsbox/ml/utils.py
dsbox/ml/calibration/__init__.py
dsbox/ml/calibration/calibration.py
dsbox/ml/ensemble/__init__.py
dsbox/ml/ensemble/rrclassifier/__init__.py
dsbox/ml/ensemble/rrclassifier/randomrotation.py
dsbox/ml/ensemble/rrclassifier/rr_extra_forest.py
dsbox/ml/ensemble/rrclassifier/rr_forest.py
dsbox/ml/explain/__init__.py
dsbox/ml/explain/feature_contributions.py
dsbox/ml/explain/prediction_interval.py
dsbox/ml/feature_engineering/__init__.py
dsbox/ml/feature_engineering/categorical.py
dsbox/ml/feature_engineering/timeseries.py
dsbox/ml/feature_selection/__init__.py
dsbox/ml/feature_selection/greedy.py
dsbox/ml/markov/__init__.py
dsbox/ml/markov/histrogramdata.py
dsbox/ml/markov/seqminer.py
dsbox/ml/markov/hmmlearn/__init__.py
dsbox/ml/markov/hmmlearn/_utils.py
dsbox/ml/markov/hmmlearn/base.py
dsbox/ml/markov/hmmlearn/hmm.py
dsbox/ml/markov/hmmlearn/stats.py
dsbox/ml/markov/hmmlearn/utils.py
dsbox/ml/markov/seqlearn/__init__.py
dsbox/ml/markov/seqlearn/base.py
dsbox/ml/markov/seqlearn/evaluation.py
dsbox/ml/markov/seqlearn/hmm.py
ds_box-1.4.5.dist-info/LICENSE
ds_box-1.4.5.dist-info/METADATA
ds_box-1.4.5.dist-info/WHEEL
ds_box-1.4.5.dist-info/top_level.txt
ds_box-1.4.5.dist-info/RECORD
