Metadata-Version: 2.1
Name: ds-box
Version: 1.4.5
Summary: Package made to accelerate data science workflows in production.
Home-page: https://github.com/vlevorato/dsbox
Author: Vincent Levorato
License: UNKNOWN
Platform: UNKNOWN
Classifier: Programming Language :: Python :: 3
Classifier: License :: OSI Approved :: Apache Software License
Classifier: Operating System :: OS Independent
Requires-Python: >=3.8
License-File: LICENSE
